office_metadata_extractor/__init__.py
office_metadata_extractor/extractor.py
office_metadata_extractor-1.0.0.dist-info/licenses/LICENSE
office_metadata_extractor-1.0.0.dist-info/METADATA
office_metadata_extractor-1.0.0.dist-info/WHEEL
office_metadata_extractor-1.0.0.dist-info/top_level.txt
office_metadata_extractor-1.0.0.dist-info/RECORD
