Metadata-Version: 2.4
Name: office_metadata_extractor
Version: 1.0.0
Summary: Extract custom/core metadata from Office (.docx, .xlsx, .pptx) files
Author-email: Sunil K Sundaram <sunilsmindspace@gmail.com>
License: MIT
Project-URL: Homepage, https://github.com/sunilsmindspace/office_metadata_extractor
Project-URL: Repository, https://github.com/sunilsmindspace/office_metadata_extractor
Requires-Python: >=3.12.3
License-File: LICENSE
Dynamic: license-file
